logsmith/__init__.py
logsmith/logsmith.py
logsmith/packages/__init__.py
logsmith/packages/constants.py
logsmith/packages/logging.py
logsmith/packages/monitor.py
logsmith/packages/utilities.py
logsmith-0.1.0.dist-info/METADATA
logsmith-0.1.0.dist-info/WHEEL
logsmith-0.1.0.dist-info/top_level.txt
logsmith-0.1.0.dist-info/RECORD
