Metadata-Version: 2.1
Name: logsmith
Version: 0.1.0
Summary: A Logging Library for Python
Home-page: https://github.com/TanmoySG/logsmith
Author: Tanmoy Sen Gupta
Author-email: tanmoysps@gmail.com
License: MIT
Keywords: imports,logs,python,logging
Platform: UNKNOWN
Classifier: Programming Language :: Python :: 3
Classifier: License :: OSI Approved :: MIT License
Classifier: Operating System :: OS Independent
Requires-Dist: termcolor (==1.1.0)
Requires-Dist: requests (==2.28.0)
